haystack_integrations/components/embedders/py.typed
haystack_integrations/components/embedders/watsonx/__init__.py
haystack_integrations/components/embedders/watsonx/document_embedder.py
haystack_integrations/components/embedders/watsonx/text_embedder.py
haystack_integrations/components/generators/py.typed
haystack_integrations/components/generators/watsonx/__init__.py
haystack_integrations/components/generators/watsonx/generator.py
haystack_integrations/components/generators/watsonx/chat/__init__.py
haystack_integrations/components/generators/watsonx/chat/chat_generator.py
watsonx_haystack-1.2.0.dist-info/METADATA
watsonx_haystack-1.2.0.dist-info/WHEEL
watsonx_haystack-1.2.0.dist-info/licenses/LICENSE.txt
watsonx_haystack-1.2.0.dist-info/RECORD
